TinyMem/__init__.py
tinymem-0.0.1.dist-info/METADATA
tinymem-0.0.1.dist-info/WHEEL
tinymem-0.0.1.dist-info/top_level.txt
tinymem-0.0.1.dist-info/RECORD
