Metadata-Version: 2.4
Name: tinymem
Version: 0.0.1
Summary: Tiny Memory.
Requires-Python: >=3.8
